eeland/__init__.py
eeland/cli.py
eeland/main.py
eeland/utils.py
eeland-2.0.2.dist-info/entry_points.txt
eeland-2.0.2.dist-info/WHEEL
eeland-2.0.2.dist-info/METADATA
eeland-2.0.2.dist-info/RECORD
